atlassian_operator/__init__.py
atlassian_operator/main.py
atlassian_operator/cli/__init__.py
atlassian_operator/cli/appApi.py
atlassian_operator/cli/appCli.py
atlassian_operator/tmpl/config/bamboo-agent.yaml
atlassian_operator/tmpl/config/bamboo.yaml
atlassian_operator/tmpl/config/bitbucket.yaml
atlassian_operator/tmpl/config/confluence.yaml
atlassian_operator/tmpl/config/jira-service-management.yaml
atlassian_operator/tmpl/config/jira-software.yaml
atlassian_operator/tmpl/config/nginx.yaml
atlassian_operator/tmpl/config/postgres.yaml
atlassian_operator/tmpl/nginx/conf.d/bamboo.conf
atlassian_operator/tmpl/nginx/conf.d/bitbucket.conf
atlassian_operator/tmpl/nginx/conf.d/confluence.conf
atlassian_operator/tmpl/nginx/conf.d/default.conf
atlassian_operator/tmpl/nginx/conf.d/jira-service-management.conf
atlassian_operator/tmpl/nginx/conf.d/jira-software.conf
atlassian_operator/tmpl/postgres/docker-entrypoint-initdb.d/init.sql
atlassian_operator/utils/__init__.py
atlassian_operator/utils/appDocker.py
atlassian_operator/utils/appLogger.py
atlassian_operator/utils/appServices.py
atlassian_operator-0.5.dist-info/licenses/LICENSE
atlassian_operator-0.5.dist-info/METADATA
atlassian_operator-0.5.dist-info/WHEEL
atlassian_operator-0.5.dist-info/entry_points.txt
atlassian_operator-0.5.dist-info/top_level.txt
atlassian_operator-0.5.dist-info/RECORD
