Metadata-Version: 2.4
Name: atlassian-operator
Version: 0.5
Summary: Deploying Atlassian Products with Docker
Author-email: Will <will.shi@tman.ltd>
Maintainer-email: Will <will.shi@tman.ltd>
Project-URL: Homepage, https://github.com/TMAN-Lab/tman-atlassian-operator
Keywords: atlassian,jira,confluence,docker,deploy,setup,cli
Classifier: Programming Language :: Python :: 3
Classifier: Operating System :: POSIX :: Linux
Requires-Python: >=3.7
License-File: LICENSE
Requires-Dist: PyYAML
Requires-Dist: tabulate
Requires-Dist: requests
Requires-Dist: argcomplete
Requires-Dist: docker
Dynamic: license-file
